{
  "Best Actor in a Motion Picture in the Comedy or Musical category for Les Miserables | winner": {
    "name": "Best Actor in a Motion Picture in the Comedy or Musical category for Les Miserables | winner",
    "nominees": [
      "GoldenGlobes"
    ],
    "votes": 1
  },
  "Best Group of Bad Asses | Best Group of Bad Asses in a Motion Picture | nominee": {
    "name": "Best Group of Bad Asses | Best Group of Bad Asses in a Motion Picture | nominee",
    "nominees": [
      "Jennifer Lawrence",
      "Anne Hathaway",
      "Daniel Day Lewis",
      "Jessica Chastain",
      "Bill Clinton",
      "Christoph Waltz",
      "Quentin Tarantino",
      "Adele",
      "Don Cheadle",
      "Damian Lewis",
      "Best Actor",
      "Claire Danes",
      "Julianne Moore",
      "GoldenGlobes",
      "Kevin Costner",
      "Lena Dunham",
      "Lawrence",
      "Best Animated Feature Film",
      "Day Lewis",
      "Les Miserables",
      "MaggieSmith",
      "Best Actress",
      "Tina Fey",
      "Maggie Smith",
      "Ed Harris",
      "Ben Affleck",
      "Score for Life of Pi",
      "Best Song",
      "Jean Valjean",
      "Bill Murray",
      "Lincoln",
      "Best Original Song",
      "Catherine Zeta Jones",
      "Cajas",
      "Damien Lewis",
      "Skyball",
      "Quentin",
      "SHOW",
      "Best Picture",
      "Selena Gomez",
      "Clinton",
      "Taylor Swift",
      "GoldenGlobes Ed Harris",
      "Best Musical",
      "Hugh Jackmon",
      "LesMiserables",
      "Best Picture &",
      "Drama",
      "Woah Ben Affleck",
      "Oscar",
      "Sofia Vergara",
      "Best Group of Bad",
      "Christopher Waltz",
      "Cristoph Waltz",
      "Supporting Actor",
      "Miniseries",
      "Best Mini Series or TV Movie",
      "HOMELAND",
      "Best Drama",
      "Mychael Danna",
      "Madonna",
      "taylor",
      "Original Song for Motion Picture",
      "Feral",
      "Mandy Patinkin",
      "John Krasinski",
      "AnneHathaway",
      "Django Unchained",
      "J. Lawrence",
      "Billy Murray",
      "Best Foreign Language Film",
      "QT",
      "Globes Jennifer Lawrence",
      "AzizAnsari",
      "Amy Poehler",
      "Amy",
      "Halle Berry",
      "-Comedy or Musical",
      "Best TV Series Comedy or Musical",
      "GIRLS",
      "Best TV Comedy",
      "Best Comedy TV Series",
      "LenaDunham",
      "Best Actor Motion Picture",
      "HughJackman",
      "Best Husband",
      "Best Actor of All",
      "Motion Picture",
      "wajib",
      "Best Pic",
      "Best Motion Picture Drama &",
      "Mitt Romney",
      "Gandhi",
      "Best Drama Film",
      "ANDREW LINCOLN",
      "Si Robertson",
      "Kate Hudson",
      "Golden Globes",
      "ActofValor",
      "Damian Fransisco",
      "BestActress",
      "Sam Jackson",
      "Best Picture Golden Globe",
      "Amanda Seyfried",
      "Tommy Lee Jones",
      "Jlo",
      "Mhissy",
      "ParaNorman",
      "AskGlobes",
      "Black Coffins",
      "Gangster Squad"
    ],
    "votes": 2
  },
  "best performance by Don Cheadle in a show nobody likes at all but it | winner": {
    "name": "best performance by Don Cheadle in a show nobody likes at all but it | winner",
    "nominees": [
      "Don Cheadle"
    ],
    "votes": 1
  },
  "Best Director right now after being snubbed of an Oscar nomination | nominee": {
    "name": "Best Director right now after being snubbed of an Oscar nomination | nominee",
    "nominees": [
      "Ben Affleck"
    ],
    "votes": 1
  },
  "Best Supporting Actress for TV performance for Downton Abbey | winner": {
    "name": "Best Supporting Actress for TV performance for Downton Abbey | winner",
    "nominees": [
      "Maggie Smith"
    ],
    "votes": 1
  },
  "best song for the theme to Skyfall and Dame Maggie Smith wi | winner": {
    "name": "best song for the theme to Skyfall and Dame Maggie Smith wi | winner",
    "nominees": [
      "Adele"
    ],
    "votes": 2
  },
  "Best Original Song at the Golden Globes in LA for Skyfall | winner": {
    "name": "Best Original Song at the Golden Globes in LA for Skyfall | winner",
    "nominees": [
      "Adele"
    ],
    "votes": 1
  },
  "Best Actress In A Supporting Role in a Motion Picture the | winner": {
    "name": "Best Actress In A Supporting Role in a Motion Picture the | winner",
    "nominees": [
      "Anne Hathaway"
    ],
    "votes": 1
  },
  "Best Supporting Actress in Silver Linings Playbook too | nominee": {
    "name": "Best Supporting Actress in Silver Linings Playbook too | nominee",
    "nominees": [
      "Jennifer Lawrence"
    ],
    "votes": 1
  },
  "Best Animated Feature Film | Best Animated Feature Film | winner": {
    "name": "Best Animated Feature Film | Best Animated Feature Film | winner",
    "nominees": [
      "Best Animated Feature Film"
    ],
    "votes": 1
  },
  "Best Performance by an Actress In A Television Series | winner": {
    "name": "Best Performance by an Actress In A Television Series | winner",
    "nominees": [
      "Claire Danes"
    ],
    "votes": 1
  },
  "Best Performance by an Actress in a TV series at the | winner": {
    "name": "Best Performance by an Actress in a TV series at the | winner",
    "nominees": [
      "Julianne Moore"
    ],
    "votes": 1
  },
  "Best Actress In A Comedy for Silver Linings Playbook | winner": {
    "name": "Best Actress In A Comedy for Silver Linings Playbook | winner",
    "nominees": [
      "Jennifer Lawrence",
      "Best Actress In A Comedy for Silver Linings Playbook"
    ],
    "votes": 1
  },
  "really excited to see if Andrew McCutchen wins a Golden Globe": {
    "name": "really excited to see if Andrew McCutchen wins a Golden Globe",
    "nominees": [
      "Andrew McCutchen"
    ],
    "votes": 1
  },
  "Best Actress | Best Actress in a Comedy TV series | winner": {
    "name": "Best Actress | Best Actress in a Comedy TV series | winner",
    "nominees": [
      "Best Actress"
    ],
    "votes": 1
  },
  "best movie comedy or musical at the Golden Globes | winner": {
    "name": "best movie comedy or musical at the Golden Globes | winner",
    "nominees": [
      "Awesome Les Miserables"
    ],
    "votes": 1
  },
  "Best Original Song | Best Original Song for this | nominee": {
    "name": "Best Original Song | Best Original Song for this | nominee",
    "nominees": [
      "Best Original Song"
    ],
    "votes": 2
  },
  "best actor in a drama at the Golden Globes in LA | winner": {
    "name": "best actor in a drama at the Golden Globes in LA | winner",
    "nominees": [
      "Damien Lewis"
    ],
    "votes": 1
  },
  "Best Actor in Tv Series Drama Golden Globes 2013 | winner": {
    "name": "Best Actor in Tv Series Drama Golden Globes 2013 | winner",
    "nominees": [
      "Damian Lewis"
    ],
    "votes": 1
  },
  "best reaction to Pimp Billy the Real 's entrance | winner": {
    "name": "best reaction to Pimp Billy the Real 's entrance | winner",
    "nominees": [
      "Pimp Billy"
    ],
    "votes": 1
  },
  "Best Performance by an Actor in a Motion Picture | winner": {
    "name": "Best Performance by an Actor in a Motion Picture | winner",
    "nominees": [
      "Daniel Day Lewis"
    ],
    "votes": 1
  },
  "Best nominee intro Kristen Wig and Will Ferrell | nominee": {
    "name": "Best nominee intro Kristen Wig and Will Ferrell | nominee",
    "nominees": [
      "Kristen Wig"
    ],
    "votes": 1
  },
  "best supporting actress for her role in Les Mis | winner": {
    "name": "best supporting actress for her role in Les Mis | winner",
    "nominees": [
      "Anne Hathaway"
    ],
    "votes": 1
  },
  "best actress in a TV series drama for Homeland | winner": {
    "name": "best actress in a TV series drama for Homeland | winner",
    "nominees": [
      "Claire Danes"
    ],
    "votes": 2
  },
  "Best Actor for a TV Series Drama for Homeland | winner": {
    "name": "Best Actor for a TV Series Drama for Homeland | winner",
    "nominees": [
      "Damian Lewis"
    ],
    "votes": 2
  },
  "Best Actor TV Comedy Series for HOUSE OF LIES | winner": {
    "name": "Best Actor TV Comedy Series for HOUSE OF LIES | winner",
    "nominees": [
      "Don Cheadle"
    ],
    "votes": 1
  },
  "Best Actor Award for the movie Lincoln at the | winner": {
    "name": "Best Actor Award for the movie Lincoln at the | winner",
    "nominees": [
      "Day Lewis"
    ],
    "votes": 1
  },
  "Best Actor Academy Award for the Hurt Locker | nominee": {
    "name": "Best Actor Academy Award for the Hurt Locker | nominee",
    "nominees": [
      "Jeremy Renner"
    ],
    "votes": 1
  },
  "Best Actress in a Miniseries for Game Change | winner": {
    "name": "Best Actress in a Miniseries for Game Change | winner",
    "nominees": [
      "Julianne Moore"
    ],
    "votes": 1
  },
  "best actor in miniseries for Hatfields & amp | winner": {
    "name": "best actor in miniseries for Hatfields & amp | winner",
    "nominees": [
      "Kevin Costner"
    ],
    "votes": 1
  },
  "Best Actor TV Series | Best Actor TV Series | nominee": {
    "name": "Best Actor TV Series | Best Actor TV Series | nominee",
    "nominees": [
      "Best Actor TV Series"
    ],
    "votes": 1
  },
  "Best Supporting Actor at Golden Globes 2013 | winner": {
    "name": "Best Supporting Actor at Golden Globes 2013 | winner",
    "nominees": [
      "Christoph Waltz"
    ],
    "votes": 1
  },
  "Best Peter Pan Haircut at the Golden Globes | winner": {
    "name": "Best Peter Pan Haircut at the Golden Globes | winner",
    "nominees": [
      "Anne Hathaway"
    ],
    "votes": 1
  },
  "Best Supporting Actress in a Motion Picture | winner": {
    "name": "Best Supporting Actress in a Motion Picture | winner",
    "nominees": [
      "Anne Hathaway",
      "Anne Hathway"
    ],
    "votes": 1
  },
  "Best Director for Argo at the Golden Globes | winner": {
    "name": "Best Director for Argo at the Golden Globes | winner",
    "nominees": [
      "Ben Affleck",
      "Academy",
      "ben afleck"
    ],
    "votes": 2
  },
  "best personality on the red carpet tonight | winner": {
    "name": "best personality on the red carpet tonight | winner",
    "nominees": [
      "Dustin Hoffman"
    ],
    "votes": 1
  },
  "Best Supporting Actor for Django Unchained | winner": {
    "name": "Best Supporting Actor for Django Unchained | winner",
    "nominees": [
      "Christoph Waltz",
      "Mychael Danna",
      "ChristophterWaltz"
    ],
    "votes": 2
  },
  "Best Actor in a Miniseries or TV Movie for | winner": {
    "name": "Best Actor in a Miniseries or TV Movie for | winner",
    "nominees": [
      "Kevin Costner"
    ],
    "votes": 1
  },
  "Best Supporting Actress for Les Miserables | winner": {
    "name": "Best Supporting Actress for Les Miserables | winner",
    "nominees": [
      "Anne Hathaway"
    ],
    "votes": 3
  },
  "Best Actress | Best Actress in a TV Series | winner": {
    "name": "Best Actress | Best Actress in a TV Series | winner",
    "nominees": [
      "Claire Danes",
      "Lena Dunham",
      "Best Actress"
    ],
    "votes": 2
  },
  "Best Actress in a Mini Series or TV movie | winner": {
    "name": "Best Actress in a Mini Series or TV movie | winner",
    "nominees": [
      "GoldenGlobes Julianne Moore"
    ],
    "votes": 1
  },
  "Best Drama after awkward technical mishap | winner": {
    "name": "Best Drama after awkward technical mishap | winner",
    "nominees": [
      "Best Drama"
    ],
    "votes": 1
  },
  "best actress in comedy or musical in film | winner": {
    "name": "best actress in comedy or musical in film | winner",
    "nominees": [
      "Lawrence",
      "Jennifer Lawrence"
    ],
    "votes": 2
  },
  "best actress in a drama television series | winner": {
    "name": "best actress in a drama television series | winner",
    "nominees": [
      "Claire Danes"
    ],
    "votes": 1
  },
  "Best Actress TV | Best Actress TV series | nominee": {
    "name": "Best Actress TV | Best Actress TV series | nominee",
    "nominees": [
      "Claire Danes Best Actress TV"
    ],
    "votes": 1
  },
  "Best Drama and Best Lead Actor here too | nominee": {
    "name": "Best Drama and Best Lead Actor here too | nominee",
    "nominees": [
      "Best Drama"
    ],
    "votes": 1
  },
  "best actress in TV drama for her work on | winner": {
    "name": "best actress in TV drama for her work on | winner",
    "nominees": [
      "Claire Danes"
    ],
    "votes": 1
  },
  "Best Original Song in the Golden Globes | winner": {
    "name": "Best Original Song in the Golden Globes | winner",
    "nominees": [
      "Best Original Song"
    ],
    "votes": 1
  },
  "Best Actor in TV Series 4\"House of Lies | winner": {
    "name": "Best Actor in TV Series 4\"House of Lies | winner",
    "nominees": [
      "Best Actor"
    ],
    "votes": 1
  },
  "Best Actress in a Motion Picture- Drama | winner": {
    "name": "Best Actress in a Motion Picture- Drama | winner",
    "nominees": [
      "Jessica Chastain"
    ],
    "votes": 1
  },
  "Best Original Song in a Motion Picture | winner": {
    "name": "Best Original Song in a Motion Picture | winner",
    "nominees": [
      "Best Original Song",
      "Best Original Song Motion Picture"
    ],
    "votes": 2
  },
  "Best TV Actress in a Comedy from Girls | winner": {
    "name": "Best TV Actress in a Comedy from Girls | winner",
    "nominees": [
      "Jack"
    ],
    "votes": 1
  },
  "Best Actress in a Miniseries or Motion Picture": {
    "name": "Best Actress in a Miniseries or Motion Picture",
    "nominees": [
      "Best Actress"
    ],
    "votes": 1
  },
  "Best Screenplay but Quentin Tarantino | winner": {
    "name": "Best Screenplay but Quentin Tarantino | winner",
    "nominees": [
      "Quentin Tarantino"
    ],
    "votes": 1
  },
  "Best Motion Picture Comedy or Musical | winner": {
    "name": "Best Motion Picture Comedy or Musical | winner",
    "nominees": [
      "GoldenGlobes Les Miserables"
    ],
    "votes": 1
  },
  "Best Supporting Actress in a TV show | winner": {
    "name": "Best Supporting Actress in a TV show | winner",
    "nominees": [
      "Maggie Smith"
    ],
    "votes": 1
  },
  "Best Actor in a TV Drama Series for | winner": {
    "name": "Best Actor in a TV Drama Series for | winner",
    "nominees": [
      "Damian Lewis"
    ],
    "votes": 1
  },
  "Best Acceptance Speech of the Night | winner": {
    "name": "Best Acceptance Speech of the Night | winner",
    "nominees": [
      "Adele"
    ],
    "votes": 1
  },
  "Best Original Screenplay for Saying | winner": {
    "name": "Best Original Screenplay for Saying | winner",
    "nominees": [
      "Quentin Tarantino"
    ],
    "votes": 1
  },
  "Best Actress in a Television Series | winner": {
    "name": "Best Actress in a Television Series | winner",
    "nominees": [
      "Claire Danes",
      "HBO"
    ],
    "votes": 1
  },
  "best director at the golden globes | nominee": {
    "name": "best director at the golden globes | nominee",
    "nominees": [
      "Ben Affleck",
      "BenAffleck",
      "Idiocy of # OscarNoms Affleck",
      "Non - Oscar",
      "Ben # Affleck",
      "GoldenGlobes",
      "Oscars",
      "ben afleck",
      "Jared Leto",
      "Hooray",
      "Yay Ben Affleck",
      "Globe",
      "Best Picture",
      "Tom Hooper",
      "the Oscars SHOULD",
      "BenAfflek",
      "Oscar",
      "Ang Lee"
    ],
    "votes": 2
  },
  "best original score for LIFE OF PI | winner": {
    "name": "best original score for LIFE OF PI | winner",
    "nominees": [
      "Michael Danna"
    ],
    "votes": 1
  },
  "best TV drama actress for Homeland | winner": {
    "name": "best TV drama actress for Homeland | winner",
    "nominees": [
      "Claire Danes"
    ],
    "votes": 1
  },
  "best actress for musical or comedy | winner": {
    "name": "best actress for musical or comedy | winner",
    "nominees": [
      "jennifer lawrence"
    ],
    "votes": 1
  },
  "Best nominee cutaway of the night | nominee": {
    "name": "Best nominee cutaway of the night | nominee",
    "nominees": [
      "Amy Poehler"
    ],
    "votes": 1
  },
  "Best Actor for Game Change but he | winner": {
    "name": "Best Actor for Game Change but he | winner",
    "nominees": [
      "Ed Harris"
    ],
    "votes": 1
  },
  "Best Actor in a Television Series | winner": {
    "name": "Best Actor in a Television Series | winner",
    "nominees": [
      "Best Actor",
      "Don Cheadle"
    ],
    "votes": 1
  },
  "Best Actress TV Series- Drama for | winner": {
    "name": "Best Actress TV Series- Drama for | winner",
    "nominees": [
      "ClaireDanes"
    ],
    "votes": 1
  },
  "Best Animated Feature Film at the | winner": {
    "name": "Best Animated Feature Film at the | winner",
    "nominees": [
      "Best Animated Feature Film"
    ],
    "votes": 1
  },
  "best actor in a comedy or musical | winner": {
    "name": "best actor in a comedy or musical | winner",
    "nominees": [
      "Best Actor"
    ],
    "votes": 1
  },
  "Best Actress for ZERO DARK THIRTY | winner": {
    "name": "Best Actress for ZERO DARK THIRTY | winner",
    "nominees": [
      "Jessica Chastain"
    ],
    "votes": 1
  },
  "Best Supporting Actress in flick | winner": {
    "name": "Best Supporting Actress in flick | winner",
    "nominees": [
      "Anne Hathaway",
      "MaggieSmith"
    ],
    "votes": 3
  },
  "Best Actess in a TV series Drama | winner": {
    "name": "Best Actess in a TV series Drama | winner",
    "nominees": [
      "Claire Danes"
    ],
    "votes": 1
  },
  "Best Actress in a TV Series for | winner": {
    "name": "Best Actress in a TV Series for | winner",
    "nominees": [
      "Lena Dunham",
      "JulianneMoore"
    ],
    "votes": 2
  },
  "Best Original Song w/ ' Skyfall | winner": {
    "name": "Best Original Song w/ ' Skyfall | winner",
    "nominees": [
      "Adele"
    ],
    "votes": 1
  },
  "Best speech of the night so far | winner": {
    "name": "Best speech of the night so far | winner",
    "nominees": [
      "Jennifer Lawrence",
      "Adele"
    ],
    "votes": 2
  },
  "best actress in a comedy series | winner": {
    "name": "best actress in a comedy series | winner",
    "nominees": [
      "Lena Dunham"
    ],
    "votes": 1
  },
  "best director for the ARGO film | winner": {
    "name": "best director for the ARGO film | winner",
    "nominees": [
      "Ben Afflect"
    ],
    "votes": 1
  },
  "Best Actor & | Best Actor & amp | winner": {
    "name": "Best Actor & | Best Actor & amp | winner",
    "nominees": [
      "Best Actor &"
    ],
    "votes": 1
  },
  "Best Actress Comedy Or Musical | nominee": {
    "name": "Best Actress Comedy Or Musical | nominee",
    "nominees": [
      "Jennifer Lawrence"
    ],
    "votes": 2
  },
  "best original song for Skyfall | winner": {
    "name": "best original song for Skyfall | winner",
    "nominees": [
      "Adele",
      "Yayyyy Adele"
    ],
    "votes": 1
  },
  "best actor in a miniseries for | winner": {
    "name": "best actor in a miniseries for | winner",
    "nominees": [
      "Kevin Costner"
    ],
    "votes": 1
  },
  "Best Actor for Hatfields & amp | winner": {
    "name": "Best Actor for Hatfields & amp | winner",
    "nominees": [
      "Kevin Costner"
    ],
    "votes": 1
  },
  "Best Actor in a Motion Picture | winner": {
    "name": "Best Actor in a Motion Picture | winner",
    "nominees": [
      "Best Actor",
      "Daniel Day Lewis",
      "Best Actor In a Motion Picture",
      "Day Lewis"
    ],
    "votes": 1
  },
  "Best Motion Picture for Comedy | winner": {
    "name": "Best Motion Picture for Comedy | winner",
    "nominees": [
      "Les Miserables"
    ],
    "votes": 2
  },
  "Best Bipartisan Freak Out Bait | winner": {
    "name": "Best Bipartisan Freak Out Bait | winner",
    "nominees": [
      "Jessica Chastain"
    ],
    "votes": 1
  },
  "best actress in a drama at the | winner": {
    "name": "best actress in a drama at the | winner",
    "nominees": [
      "Claire Danes",
      "Jessica Chastain",
      "Clare Danes"
    ],
    "votes": 3
  },
  "best lead actor in a drama for | winner": {
    "name": "best lead actor in a drama for | winner",
    "nominees": [
      "Daniel Day Lewis"
    ],
    "votes": 1
  },
  "best nominee in this category | nominee": {
    "name": "best nominee in this category | nominee",
    "nominees": [
      "Schmidt"
    ],
    "votes": 1
  },
  "best Screenplay well deserved | winner": {
    "name": "best Screenplay well deserved | winner",
    "nominees": [
      "Quentin Tarantino"
    ],
    "votes": 1
  },
  "Best Performance In TV Series | winner": {
    "name": "Best Performance In TV Series | winner",
    "nominees": [
      "Claire Danes"
    ],
    "votes": 1
  },
  "best actor for Les Miserables | winner": {
    "name": "best actor for Les Miserables | winner",
    "nominees": [
      "Hugh Jackman"
    ],
    "votes": 1
  },
  "Best Picture by Foreign Press | winner": {
    "name": "Best Picture by Foreign Press | winner",
    "nominees": [
      "Best Picture by Foreign Press"
    ],
    "votes": 1
  },
  "best actor for Lez Messyrobla | winner": {
    "name": "best actor for Lez Messyrobla | winner",
    "nominees": [
      "Lez Messyrobla"
    ],
    "votes": 1
  },
  "Best Actor for performance in | winner": {
    "name": "Best Actor for performance in | winner",
    "nominees": [
      "Daniel Day Lewis"
    ],
    "votes": 1
  },
  "Best Director Oscar and just | nominee": {
    "name": "Best Director Oscar and just | nominee",
    "nominees": [
      "Ben Affleck"
    ],
    "votes": 1
  },
  "Best Animation Golden Globes | winner": {
    "name": "Best Animation Golden Globes | winner",
    "nominees": [
      "Best Animation Golden Globes"
    ],
    "votes": 1
  },
  "Best Actress in a TV comedy | nominee": {
    "name": "Best Actress in a TV comedy | nominee",
    "nominees": [
      "GoldenGlobes",
      "Best Actress"
    ],
    "votes": 2
  },
  "best director for Ben Afleck | winner": {
    "name": "best director for Ben Afleck | winner",
    "nominees": [
      "Ben Afleck"
    ],
    "votes": 1
  },
  "Best Television Show Musical | winner": {
    "name": "Best Television Show Musical | winner",
    "nominees": [
      "XOXOXOXO"
    ],
    "votes": 1
  },
  "Best Musical or Comedy after | winner": {
    "name": "Best Musical or Comedy after | winner",
    "nominees": [
      "LesMiserables",
      "Les Miserables"
    ],
    "votes": 2
  },
  "Best Picture at the Golden Globes but": {
    "name": "Best Picture at the Golden Globes but",
    "nominees": [
      "Best Picture"
    ],
    "votes": 1
  },
  "Best Miniseries or TV Movie | winner": {
    "name": "Best Miniseries or TV Movie | winner",
    "nominees": [
      "Best Miniseries or TV Movie"
    ],
    "votes": 1
  },
  "Best TV Movie or Miniseries | winner": {
    "name": "Best TV Movie or Miniseries | winner",
    "nominees": [
      "Best TV Movie"
    ],
    "votes": 1
  },
  "best actress for miniseries | winner": {
    "name": "best actress for miniseries | winner",
    "nominees": [
      "Julianna Moore"
    ],
    "votes": 1
  },
  "Best Picture due to a typo | nominee": {
    "name": "Best Picture due to a typo | nominee",
    "nominees": [
      "Fargo"
    ],
    "votes": 1
  },
  "Best Actress Motion Picture | winner": {
    "name": "Best Actress Motion Picture | winner",
    "nominees": [
      "JenniferLawrence"
    ],
    "votes": 1
  },
  "best Best Television Comedy | winner": {
    "name": "best Best Television Comedy | winner",
    "nominees": [
      "Television Comedy"
    ],
    "votes": 1
  },
  "best narration in a hockey | nominee": {
    "name": "best narration in a hockey | nominee",
    "nominees": [
      "GoldenGlobes"
    ],
    "votes": 1
  },
  "best mini series/ TV movie | winner": {
    "name": "best mini series/ TV movie | winner",
    "nominees": [
      "GoldenGlobes"
    ],
    "votes": 1
  },
  "best supporting actress at | winner": {
    "name": "best supporting actress at | winner",
    "nominees": [
      "Anne Hathaway",
      "Christoph Waltz",
      "Maggie Smith",
      "Best Supporting Actress",
      "AnneHathaway",
      "Waltz",
      "GoldenGlobes Anne Hathaway",
      "Hathaway"
    ],
    "votes": 4
  },
  "best Screenplay for Django | winner": {
    "name": "best Screenplay for Django | winner",
    "nominees": [
      "Quentin Tarantino",
      "Screenplay for Django"
    ],
    "votes": 2
  },
  "best foreign language film | winner": {
    "name": "best foreign language film | winner",
    "nominees": [
      "Best Foreign Language Film",
      "Best Foreign Film"
    ],
    "votes": 2
  },
  "best animated feature film | winner": {
    "name": "best animated feature film | winner",
    "nominees": [
      "Best Animated Film",
      "Best Animated Feature Film",
      "Best Animated Feature"
    ],
    "votes": 3
  },
  "Best Actress for TV series | winner": {
    "name": "Best Actress for TV series | winner",
    "nominees": [
      "Lena Dunham"
    ],
    "votes": 1
  },
  "Best Picture at the Oscars | winner": {
    "name": "Best Picture at the Oscars | winner",
    "nominees": [
      "Oscars"
    ],
    "votes": 1
  },
  "best motion picture drama | nominee": {
    "name": "best motion picture drama | nominee",
    "nominees": [
      "Ben Affleck"
    ],
    "votes": 1
  },
  "best original song at the | winner": {
    "name": "best original song at the | winner",
    "nominees": [
      "Adele",
      "Song",
      "Queen Madonna",
      "GoldenGlobes"
    ],
    "votes": 2
  },
  "Best Actress for Homeland | winner": {
    "name": "Best Actress for Homeland | winner",
    "nominees": [
      "Claire Danes"
    ],
    "votes": 1
  },
  "Best Drama TV Actress for | winner": {
    "name": "Best Drama TV Actress for | winner",
    "nominees": [
      "Claire Danes"
    ],
    "votes": 1
  },
  "Best Actor in a drama for | winner": {
    "name": "Best Actor in a drama for | winner",
    "nominees": [
      "Daniel Day Lewis"
    ],
    "votes": 1
  },
  "Best Featured Actress for | winner": {
    "name": "Best Featured Actress for | winner",
    "nominees": [
      "Best Actor"
    ],
    "votes": 1
  },
  "Best Supporting Actor in | winner": {
    "name": "Best Supporting Actor in | winner",
    "nominees": [
      "Christoph Waltz"
    ],
    "votes": 1
  },
  "Best Actress in TV Movie | winner": {
    "name": "Best Actress in TV Movie | winner",
    "nominees": [
      "Julianne Moore"
    ],
    "votes": 1
  },
  "Best Comedy or Musicial | nominee": {
    "name": "Best Comedy or Musicial | nominee",
    "nominees": [
      "LesMiserables"
    ],
    "votes": 1
  },
  "Best awards moment ever | nominee": {
    "name": "Best awards moment ever | nominee",
    "nominees": [
      "Amy Poehler"
    ],
    "votes": 1
  },
  "Best musical score just | nominee": {
    "name": "Best musical score just | nominee",
    "nominees": [
      "GoldenGlobes"
    ],
    "votes": 1
  },
  "best picture nominee at | nominee": {
    "name": "best picture nominee at | nominee",
    "nominees": [
      "Bill Clinton"
    ],
    "votes": 1
  },
  "Best Actor in a TV show | winner": {
    "name": "Best Actor in a TV show | winner",
    "nominees": [
      "Jon Hamm"
    ],
    "votes": 1
  },
  "Best Actor in TV series | winner": {
    "name": "Best Actor in TV series | winner",
    "nominees": [
      "Don Cheadle"
    ],
    "votes": 1
  },
  "Best Foreign Film | via | winner": {
    "name": "Best Foreign Film | via | winner",
    "nominees": [
      "Best Foreign Film"
    ],
    "votes": 1
  },
  "Best Actress in a Drama | winner": {
    "name": "Best Actress in a Drama | winner",
    "nominees": [
      "Claire Danes",
      "Jessica Chastain"
    ],
    "votes": 3
  },
  "Best Actor in a Musical | winner": {
    "name": "Best Actor in a Musical | winner",
    "nominees": [
      "Best Actor",
      "Kevin Costner"
    ],
    "votes": 2
  },
  "best film in the comedy | winner": {
    "name": "best film in the comedy | winner",
    "nominees": [
      "Les Miserables"
    ],
    "votes": 1
  },
  "Best Original Song for | winner": {
    "name": "Best Original Song for | winner",
    "nominees": [
      "Adele"
    ],
    "votes": 1
  },
  "best acceptance speech | winner": {
    "name": "best acceptance speech | winner",
    "nominees": [
      "Adele"
    ],
    "votes": 1
  },
  "best facial expression | winner": {
    "name": "best facial expression | winner",
    "nominees": [
      "Tommy Lee Jones"
    ],
    "votes": 1
  },
  "Best Actress in Comedy | winner": {
    "name": "Best Actress in Comedy | winner",
    "nominees": [
      "Jennifer Lawrence"
    ],
    "votes": 2
  },
  "best movie of the year | winner": {
    "name": "best movie of the year | winner",
    "nominees": [
      "JenniferLawrence"
    ],
    "votes": 1
  },
  "best actor in a comedy | winner": {
    "name": "best actor in a comedy | winner",
    "nominees": [
      "Best Actor",
      "Don Cheadle"
    ],
    "votes": 1
  },
  "best TV comedy actress | winner": {
    "name": "best TV comedy actress | winner",
    "nominees": [
      "Lena Dunham"
    ],
    "votes": 1
  },
  "Best Director for Argo | winner": {
    "name": "Best Director for Argo | winner",
    "nominees": [
      "Ben Affleck",
      "BenAffleck"
    ],
    "votes": 1
  },
  "Best Actor for a movie | winner": {
    "name": "Best Actor for a movie | winner",
    "nominees": [
      "Best Actor"
    ],
    "votes": 1
  },
  "best comedy or musical | winner": {
    "name": "best comedy or musical | winner",
    "nominees": [
      "Les Miserables",
      "Best Comedy or Musical"
    ],
    "votes": 1
  },
  "best actor for Lincoln | winner": {
    "name": "best actor for Lincoln | winner",
    "nominees": [
      "Daniel Day Lewis"
    ],
    "votes": 1
  },
  "Best Actor in a Drama | winner": {
    "name": "Best Actor in a Drama | winner",
    "nominees": [
      "Damian Lewis",
      "Daniel Day Lewis",
      "Day Lewis"
    ],
    "votes": 2
  },
  "best picture and DDL | nominee": {
    "name": "best picture and DDL | nominee",
    "nominees": [
      "Lincoln"
    ],
    "votes": 1
  },
  "best actress in mini | winner": {
    "name": "best actress in mini | winner",
    "nominees": [
      "Julianne Moore",
      "Claire Danes"
    ],
    "votes": 2
  },
  "Best TV Drama Series | winner": {
    "name": "Best TV Drama Series | winner",
    "nominees": [
      "Best TV Drama Series"
    ],
    "votes": 1
  },
  "best director at the | winner": {
    "name": "best director at the | winner",
    "nominees": [
      "Ben Affleck",
      "Tarentino"
    ],
    "votes": 1
  },
  "best actor for Les Mis-- well": {
    "name": "best actor for Les Mis-- well",
    "nominees": [
      "Les Mis--"
    ],
    "votes": 1
  },
  "best original score | winner": {
    "name": "best original score | winner",
    "nominees": [
      "GoldenGlobes Life",
      "Best Original Score",
      "LifeOfPie"
    ],
    "votes": 1
  },
  "best original song | nominee": {
    "name": "best original song | nominee",
    "nominees": [
      "Jon Bon Jovi",
      "Song",
      "Adele"
    ],
    "votes": 1
  },
  "Best Director prize | winner": {
    "name": "Best Director prize | winner",
    "nominees": [
      "Ben Affleck"
    ],
    "votes": 1
  },
  "Best Motion PIcture | winner": {
    "name": "Best Motion PIcture | winner",
    "nominees": [
      "Les Miserables",
      "LesMiserables",
      "Ben Affleck",
      "Motion Picture"
    ],
    "votes": 1
  },
  "Best Picture Comedy | winner": {
    "name": "Best Picture Comedy | winner",
    "nominees": [
      "Les Miserables"
    ],
    "votes": 1
  },
  "Best Animated film | nominee": {
    "name": "Best Animated film | nominee",
    "nominees": [
      "Best Animated Film",
      "Animated Film",
      "Best Animated"
    ],
    "votes": 1
  },
  "best picture but I | nominee": {
    "name": "best picture but I | nominee",
    "nominees": [
      "GoldenGlobes",
      "Django Unchained"
    ],
    "votes": 2
  },
  "Best Actress Award | winner": {
    "name": "Best Actress Award | winner",
    "nominees": [
      "Jennifer Lawrence",
      "Claire Danes",
      "Jessica Chastain"
    ],
    "votes": 3
  },
  "Best Gauze Bandage | winner": {
    "name": "Best Gauze Bandage | winner",
    "nominees": [
      "Amanda Seyfried",
      "LOLOL Amanda Seyfried"
    ],
    "votes": 1
  },
  "best speech writer | winner": {
    "name": "best speech writer | winner",
    "nominees": [
      "Mel Gibson"
    ],
    "votes": 1
  },
  "best film nominee | nominee": {
    "name": "best film nominee | nominee",
    "nominees": [
      "Jeremy Irons"
    ],
    "votes": 1
  },
  "Best Actor Comedy | winner": {
    "name": "Best Actor Comedy | winner",
    "nominees": [
      "Best Actor Comedy"
    ],
    "votes": 1
  },
  "best award speech | winner": {
    "name": "best award speech | winner",
    "nominees": [
      "Day Lewis"
    ],
    "votes": 1
  },
  "best exotic marigold hotel": {
    "name": "best exotic marigold hotel",
    "nominees": [
      "Exotic Marigold Hotel"
    ],
    "votes": 1
  },
  "Best Miniseries | nominee": {
    "name": "Best Miniseries | nominee",
    "nominees": [
      "Best Miniseries",
      "Jessica Lange",
      "GoldenGlobes",
      "Jodie Foster 's"
    ],
    "votes": 2
  },
  "best song at the | winner": {
    "name": "best song at the | winner",
    "nominees": [
      "Best Song",
      "Adele",
      "Yaaaaay"
    ],
    "votes": 1
  },
  "Best Actor Miniseries and": {
    "name": "Best Actor Miniseries and",
    "nominees": [
      "Kevin Costner"
    ],
    "votes": 1
  },
  "Best Drama Movie | winner": {
    "name": "Best Drama Movie | winner",
    "nominees": [
      "Best Drama Movie"
    ],
    "votes": 1
  },
  "best show on tv | nominee": {
    "name": "best show on tv | nominee",
    "nominees": [
      "GoldenGlobes"
    ],
    "votes": 1
  },
  "Best Supporting | winner": {
    "name": "Best Supporting | winner",
    "nominees": [
      "Christoph Waltz",
      "Anne Hathaway"
    ],
    "votes": 1
  },
  "Best Comedy at | winner": {
    "name": "Best Comedy at | winner",
    "nominees": [
      "Les Miserables",
      "Best Comedy",
      "Comedy",
      "LesMiserables",
      "Les Miserable"
    ],
    "votes": 2
  },
  "best tv series | winner": {
    "name": "best tv series | winner",
    "nominees": [
      "GIRLS"
    ],
    "votes": 1
  },
  "best bit ever | nominee": {
    "name": "best bit ever | nominee",
    "nominees": [
      "Amy Poehler"
    ],
    "votes": 1
  },
  "Best tv movie | nominee": {
    "name": "Best tv movie | nominee",
    "nominees": [
      "Liz &"
    ],
    "votes": 1
  },
  "Best TV Movie | winner": {
    "name": "Best TV Movie | winner",
    "nominees": [
      "HBO",
      "Les Miserables"
    ],
    "votes": 2
  },
  "Best Drama TV | winner": {
    "name": "Best Drama TV | winner",
    "nominees": [
      "GoldenGlobes",
      "Best Drama"
    ],
    "votes": 3
  },
  "best necklace | winner": {
    "name": "best necklace | winner",
    "nominees": [
      "Jessica Alba"
    ],
    "votes": 1
  },
  "Best Actress | nominee": {
    "name": "Best Actress | nominee",
    "nominees": [
      "Best Actress",
      "NONE",
      "Best Actress - Musical"
    ],
    "votes": 1
  },
  "best picture | winner": {
    "name": "best picture | winner",
    "nominees": [
      "Les Miserables",
      "Les Miz",
      "LesMis",
      "GoldenGlobes",
      "GoldenGlobes Les Miserables",
      "BEST PICTURE - MUSIC OR",
      "Arsego"
    ],
    "votes": 1
  },
  "best awards | nominee": {
    "name": "best awards | nominee",
    "nominees": [
      "Amy"
    ],
    "votes": 1
  },
  "best comedy | nominee": {
    "name": "best comedy | nominee",
    "nominees": [
      "GoldenGlobes",
      "Best Comedy"
    ],
    "votes": 1
  },
  "Best Drama | nominee": {
    "name": "Best Drama | nominee",
    "nominees": [
      "Newsroom"
    ],
    "votes": 1
  },
  "Best Song | nominee": {
    "name": "Best Song | nominee",
    "nominees": [
      "Best Song",
      "GoldenGlobes",
      "Safe &"
    ],
    "votes": 1
  },
  "Best Score | winner": {
    "name": "Best Score | winner",
    "nominees": [
      "Mychael Danna"
    ],
    "votes": 1
  },
  "best nominee to not": {
    "name": "best nominee to not",
    "nominees": [
      "GoldenGlobes"
    ],
    "votes": 1
  },
  "best film | nominee": {
    "name": "best film | nominee",
    "nominees": [
      "GoldenGlobes"
    ],
    "votes": 1
  },
  "best mini | winner": {
    "name": "best mini | winner",
    "nominees": [
      "GameChange",
      "Best Mini",
      "GoldenGlobes Game Change"
    ],
    "votes": 1
  },
  "Best Supp | winner": {
    "name": "Best Supp | winner",
    "nominees": [
      "Adele",
      "Christoph Waltz"
    ],
    "votes": 1
  },
  "best Life | winner": {
    "name": "best Life | winner",
    "nominees": [
      "Bill Murray",
      "Ben Affleck"
    ],
    "votes": 2
  },
  "Michael J. Fox |": {
    "name": "Michael J. Fox |",
    "nominees": [
      "Michael J. Fox"
    ],
    "votes": 1
  },
  "Best | winner": {
    "name": "Best | winner",
    "nominees": [
      "Adele",
      "Julianne",
      "LINCOLN",
      "Anne Hathaway",
      "Don Cheadle",
      "GoldenGlobes",
      "DDL"
    ],
    "votes": 1
  },
  "every": {
    "name": "every",
    "nominees": [
      "Maggie Smith",
      "Everytime Life",
      "jessica alba",
      "Walter White",
      "Lewis"
    ],
    "votes": 1
  }
}